steammanager/__init__.py
steammanager/__main__.py
steammanager-0.6.dist-info/METADATA
steammanager-0.6.dist-info/WHEEL
steammanager-0.6.dist-info/top_level.txt
steammanager-0.6.dist-info/RECORD
