Metadata-Version: 2.1
Name: steammanager
Version: 0.6
Summary: Steam Shortcut Manager
Home-page: https://gitlab.com/avalonparton/steam-shortcut-manager
Author: Avalon Parton
Author-email: avalonlee@gmail.com
License: MIT
Platform: UNKNOWN
Requires-Dist: steamclient
